confdaora/__init__.py
confdaora/confdaora.py
confdaora/exceptions.py
confdaora/py.typed
confdaora/tests/test_dict_loader.py
confdaora/tests/test_environ_loader.py
confdaora-0.2.1.dist-info/LICENSE
confdaora-0.2.1.dist-info/WHEEL
confdaora-0.2.1.dist-info/METADATA
confdaora-0.2.1.dist-info/RECORD
