Metadata-Version: 2.1
Name: confdaora
Version: 0.2.1
Summary: confdaora
Home-page: https://github.com/dutradda/confdaora
License: UNKNOWN
Author: Diogo Dutra
Author-email: diogodutradamata@gmai.com
Requires-Python: >=3.7
Classifier: License :: OSI Approved :: MIT License
Classifier: Development Status :: 1 - Planning
Classifier: Intended Audience :: Developers
Classifier: Programming Language :: Python :: 3.8
Classifier: Topic :: Software Development :: Libraries
Requires-Dist: jsondaora
Requires-Dist: mkdocs ; extra == "doc"
Requires-Dist: mkdocs-material ; extra == "doc"
Requires-Dist: markdown-include ; extra == "doc"
Requires-Dist: black ; extra == "test"
Requires-Dist: bumpversion ; extra == "test"
Requires-Dist: flake8 ; extra == "test"
Requires-Dist: isort ; extra == "test"
Requires-Dist: ipython ; extra == "test"
Requires-Dist: mypy ; extra == "test"
Requires-Dist: pytest-cov ; extra == "test"
Requires-Dist: pytest-mock ; extra == "test"
Requires-Dist: pytest>=5.1.1 ; extra == "test"
Requires-Dist: tox ; extra == "test"
Project-URL: Documentation, https://dutradda.github.io/confdaora/
Provides-Extra: doc
Provides-Extra: test
